ssf/__init__.py
ssf/ampm.tsv
ssf/currencies.json
ssf/daymonth.tsv
ssf/daymonth.tsv.gz
ssf/daymonth00.tsv.gz
ssf/daymonth01.tsv.gz
ssf/daymonth02.tsv.gz
ssf/daymonth03.tsv.gz
ssf/daymonth04.tsv.gz
ssf/daymonth05.tsv.gz
ssf/daymonth06.tsv.gz
ssf/daymonth07.tsv.gz
ssf/daymonth08.tsv.gz
ssf/daymonth08_leap.tsv.gz
ssf/daymonth09.tsv.gz
ssf/daymonth0A.tsv.gz
ssf/daymonth0B.tsv.gz
ssf/daymonth0C.tsv.gz
ssf/daymonth0E.tsv.gz
ssf/daymonth0E_leap.tsv.gz
ssf/daymonth11.tsv.gz
ssf/daymonth11_leap.tsv.gz
ssf/daymonth12.tsv.gz
ssf/daymonth12_leap.tsv.gz
ssf/daymonth13.tsv.gz
ssf/daymonth13_leap.tsv.gz
ssf/daymonth17.tsv.gz
ssf/dbnum.tsv
ssf/eras.tsv
ssf/lc_all.tsv.gz
ssf/lcid.tsv
ssf/localize_table.yaml
ssf/lunarcal.bin
ssf/lunarcal.tsv.gz
ssf/numbers.tsv
ssf/ssf.py
ssf/ssf_calendar.py
ssf/umcal.bin
ssf-0.2.2.dist-info/AUTHORS.rst
ssf-0.2.2.dist-info/LICENSE
ssf-0.2.2.dist-info/METADATA
ssf-0.2.2.dist-info/WHEEL
ssf-0.2.2.dist-info/top_level.txt
ssf-0.2.2.dist-info/RECORD
